{
  "dialogue_id": "voss_first_meeting",
  "npc_id": "voss",
  "start_node": "start",
  "context": "Квартирмейстер Галрен Восс в Оплоті. Холодний чиновник, що приховує записи про відведене зерно.",
  "nodes": {
    "start": {
      "speaker": "Восс",
      "text": "*Перебирає папери за столом. Навіть не піднімає очей.*\n\nВартовий. Чудово. Ще один, хто хоче знати, куди поділось зерно.\n\n*Нарешті дивиться на тебе — погляд втомлений, але гострий.*\n\nУ мене немає відповідей. У мене є черги за раціоном і натовп, готовий розірвати варту на шматки.",
      "choices": [
        {
          "text": "Я хочу побачити конвойні книги.",
          "next_node": "refuse_books"
        },
        {
          "text": "Хто міг напасти на конвой?",
          "next_node": "blame_smugglers"
        },
        {
          "text": "Люди голодують. Ти можеш допомогти.",
          "next_node": "voss_pressure"
        }
      ]
    },
    "refuse_books": {
      "speaker": "Восс",
      "text": "*Завмирає на секунду. Потім — спокійно:*\n\nКонвойні книги — внутрішня документація. Не для сторонніх.\n\n*Але ти помічаєш: він не каже «не можна». Він каже «не для сторонніх». Різниця.*",
      "choices": [
        {
          "text": "Ти щось приховуєш. Я бачу.",
          "next_node": "voss_cracks",
          "condition": {"type": "flag", "flag": "investigated_grain"}
        },
        {
          "text": "А якщо я отримаю дозвіл з фортеці-міста?",
          "next_node": "voss_loophole"
        },
        {
          "text": "Добре. Поговоримо про інше.",
          "next_node": "voss_deflects"
        }
      ]
    },
    "blame_smugglers": {
      "speaker": "Восс",
      "text": "*Пожвавлюється.*\n\nКонтрабандисти. Вони крадуть усе, що пливе річкою. Затонула Сторожова Дорога — їхня територія.\n\nЯ оголосив винагороду за докази. Поки що — нічого конкретного.\n\n*Занадто швидко. Занадто охоче.*",
      "consequences": {
        "set_flag": "voss_blamed_smugglers"
      },
      "next": "voss_offer"
    },
    "voss_pressure": {
      "speaker": "Восс",
      "text": "*Вперше — без маски.*\n\nТи думаєш, я не знаю, що вони голодують? Я бачу їх щодня. Я рахую кожен мішок.\n\nАле якщо я відкрию книги зараз — почнеться паніка. А паніка вб'є більше людей, ніж голод.\n\n*Це не виправдання. Це його правда.*",
      "consequences": {
        "set_flag": "voss_showed_truth"
      },
      "next": "voss_offer"
    },
    "voss_cracks": {
      "speaker": "Восс",
      "text": "*Довга пауза. Потім — тихо:*\n\nЧастина зерна... ніколи не мала потрапити до публічних сховищ. Це не моє рішення. Я виконував наказ.\n\n*Піднімає очі.*\n\nАле конвой мав дійти. Те, що сталось на дорозі — не за планом. Це... інше.",
      "consequences": {
        "set_flag": ["voss_confessed_diversion", "grain_was_diverted"]
      },
      "next": "voss_offer"
    },
    "voss_loophole": {
      "speaker": "Восс",
      "text": "*Криво посміхається.*\n\nДозвіл із фортеці-міста? Тоді — будь ласка. Але поки його немає — книги закриті.\n\n*Він знає, що це неможливо. Але двері лишив відчиненими.*"
    },
    "voss_deflects": {
      "speaker": "Восс",
      "text": "*Киває — повертається до паперів.*\n\nРозумне рішення. У мене багато роботи."
    },
    "voss_offer": {
      "speaker": "Восс",
      "text": "*Дістає з шухляди аркуш із печаткою.*\n\nЯ можу дати тобі доступ до сховищ — обмежений. Або письмове повноваження для розслідування.\n\nАле якщо ти знайдеш тих, хто це зробив — я хочу знати першим. Не фортеця-місто. Я.",
      "choices": [
        {
          "text": "Домовились. Давай повноваження.",
          "next_node": "voss_gives_auth",
          "consequences": {"set_flag": "voss_granted_authority"}
        },
        {
          "text": "Спочатку — правда про відведене зерно.",
          "next_node": "voss_cracks",
          "condition": {"type": "not_flag", "flag": "grain_was_diverted"}
        },
        {
          "text": "Ні. Я працюю сам.",
          "next_node": "voss_alone"
        }
      ]
    },
    "voss_gives_auth": {
      "speaker": "Восс",
      "text": "*Простягає папір.*\n\nТримай. І... будь обережний на Сторожовій Дорозі. Там не тільки контрабандисти.",
      "consequences": {
        "set_flag": "voss_granted_authority"
      }
    },
    "voss_alone": {
      "speaker": "Восс",
      "text": "*Ховає папір назад.*\n\nЯк знаєш. Але без повноважень ти — просто чужинець із мечем. А тут цього недостатньо."
    }
  }
}
